{
  "pg_mhf4k7s6": {
    "cents": 0,
    "tokens": 0,
    "ts": 1761931564137
  },
  "pg_mhf4k7sd": {
    "cents": 0,
    "tokens": 0,
    "ts": 1761931564141
  },
  "pg_mhf4k7sg": {
    "cents": 0,
    "tokens": 0,
    "ts": 1761931564146
  },
  "pg_mhf4k7sk": {
    "cents": 0,
    "tokens": 0,
    "ts": 1761931564150
  },
  "pg_mhf4k7sp": {
    "cents": 0,
    "tokens": 0,
    "ts": 1761931564154
  },
  "pg_mhf4k7st": {
    "cents": 0,
    "tokens": 0,
    "ts": 1761931564158
  },
  "pg_mhf4k8iz": {
    "cents": 0,
    "tokens": 0,
    "ts": 1761931565100
  },
  "pg_mhf4k8j4": {
    "cents": 0,
    "tokens": 0,
    "ts": 1761931565105
  },
  "pg_mhf4k8ja": {
    "cents": 0,
    "tokens": 0,
    "ts": 1761931565111
  },
  "pg_mhf4k99r": {
    "cents": 0,
    "tokens": 0,
    "ts": 1761931566064
  },
  "pg_mhf4k9a5": {
    "cents": 0,
    "tokens": 0,
    "ts": 1761931566077
  },
  "pg_mhf4k9aa": {
    "cents": 0,
    "tokens": 0,
    "ts": 1761931566083
  }
}